blinktrade/__init__.py
blinktrade/clients.py
blinktrade/consts.py
blinktrade/exceptions.py
blinktrade-0.1.0.dist-info/DESCRIPTION.rst
blinktrade-0.1.0.dist-info/METADATA
blinktrade-0.1.0.dist-info/RECORD
blinktrade-0.1.0.dist-info/WHEEL
blinktrade-0.1.0.dist-info/metadata.json
blinktrade-0.1.0.dist-info/top_level.txt
tests/__init__.py
tests/auth_client_test.py
tests/open_client_test.py
